ovos_backend_client/__init__.py
ovos_backend_client/api.py
ovos_backend_client/cloud.py
ovos_backend_client/config.py
ovos_backend_client/database.py
ovos_backend_client/exceptions.py
ovos_backend_client/identity.py
ovos_backend_client/pairing.py
ovos_backend_client/settings.py
ovos_backend_client/version.py
ovos_backend_client/backends/__init__.py
ovos_backend_client/backends/base.py
ovos_backend_client/backends/offline.py
ovos_backend_client/backends/personal.py
ovos_backend_client-1.0.1.dist-info/LICENSE
ovos_backend_client-1.0.1.dist-info/METADATA
ovos_backend_client-1.0.1.dist-info/WHEEL
ovos_backend_client-1.0.1.dist-info/top_level.txt
ovos_backend_client-1.0.1.dist-info/RECORD
