Metadata-Version: 2.1
Name: ovos-backend-client
Version: 1.0.1
Summary: api client for supported ovos-core backends
Home-page: https://github.com/OpenVoiceOS/ovos-backend-client
Author: jarbasai
Author-email: jarbasai@mailfence.com
License: Apache2
Platform: UNKNOWN
Requires-Dist: ovos-utils<1.0.0,>=0.0.37
Requires-Dist: ovos-config<1.0.0,>=0.0.12
Requires-Dist: json-database~=0.7
Requires-Dist: oauthlib~=3.2
Provides-Extra: offline
Requires-Dist: timezonefinder; extra == "offline"
Requires-Dist: ovos-plugin-manager<1.0.0,>=0.0.23; extra == "offline"
Requires-Dist: SpeechRecognition~=3.8; extra == "offline"
